pycash/__init__.py
pycash-0.0.1b0.dist-info/LICENSE
pycash-0.0.1b0.dist-info/METADATA
pycash-0.0.1b0.dist-info/WHEEL
pycash-0.0.1b0.dist-info/top_level.txt
pycash-0.0.1b0.dist-info/RECORD
